dockclean/__init__.py
dockclean/containers.py
dockclean/images.py
dockclean-1.0.0b0.data/scripts/dockclean
dockclean-1.0.0b0.dist-info/METADATA
dockclean-1.0.0b0.dist-info/WHEEL
dockclean-1.0.0b0.dist-info/top_level.txt
dockclean-1.0.0b0.dist-info/RECORD
